tsk_monster/__init__.py
tsk_monster-0.0.55.dist-info/METADATA
tsk_monster-0.0.55.dist-info/WHEEL
tsk_monster-0.0.55.dist-info/entry_points.txt
tsk_monster-0.0.55.dist-info/RECORD
