Metadata-Version: 2.1
Name: tsk-monster
Version: 0.0.55
Summary: 
Author: Gilad Kutiel
Author-email: giladk@mobileye.com
Requires-Python: >=3.10,<4.0
Classifier: Programming Language :: Python :: 3
Classifier: Programming Language :: Python :: 3.10
Classifier: Programming Language :: Python :: 3.11
Classifier: Programming Language :: Python :: 3.12
Requires-Dist: dill (>=0.3.8,<0.4.0)
Requires-Dist: typer (>=0.12.3,<0.13.0)
Project-URL: Documentation, https://tsk.monster
Project-URL: Homepage, https://tsk.monster
Project-URL: Repository, https://github.com/tsk-monster/tsk
